eipiphany_file/__init__.py
eipiphany_file/component/__init__.py
eipiphany_file/component/file_configuration.py
eipiphany_file/component/file_endpoint.py
eipiphany_file/component/file_source.py
eipiphany_file-0.1.0.dev20230306154257.dist-info/METADATA
eipiphany_file-0.1.0.dev20230306154257.dist-info/WHEEL
eipiphany_file-0.1.0.dev20230306154257.dist-info/top_level.txt
eipiphany_file-0.1.0.dev20230306154257.dist-info/RECORD
